nenlib/__init__.py
nenlib/config.py
nenlib/mlops.py
nenlib/constants/__init__.py
nenlib/constants/models.py
nenlib/helpers/__init__.py
nenlib/helpers/utils.py
nenlib/logging/__init__.py
nenlib/logging/logger.py
nenlib/mlops/__init__.py
nenlib/mlops/litellm.py
nenlib/mlops/providers.py
nenlib-0.2.0.dist-info/METADATA
nenlib-0.2.0.dist-info/WHEEL
nenlib-0.2.0.dist-info/licenses/LICENSE
nenlib-0.2.0.dist-info/RECORD
