Metadata-Version: 2.4
Name: nenlib
Version: 0.2.0
Summary: Utilities and helpers for LLMOps with LiteLLM integration
Author-email: Your Name <your.email@example.com>
License: MIT License
License-File: LICENSE
Requires-Dist: litellm[proxy]>=1.0.0
Provides-Extra: dev
Requires-Dist: isort>=5.12.0; extra == 'dev'
Requires-Dist: pytest>=7.0.0; extra == 'dev'
Requires-Dist: pyyaml>=6.0.0; extra == 'dev'
Requires-Dist: ruff>=0.4.0; extra == 'dev'
